[
{"Name": "Bảo tàng điêu khắc Champa"},
{"Name": "Bán đảo Sơn Trà"},
{"Name": "Bà Nà Hills"},
{"Name": "Công viên bảo tồn động vật và chim hoang dã Langkawi (Langkawi Wildlife Park and Bird Paradise)"},
{"Name": "Công viên động vật hoang dã Featherdale"},
{"Name": "Trung tâm Bảo tồn và cứu hộ động vật hoang dã Palawan"},
{"Name": "Bãi biển Mỹ Khê"},
{"Name": "Đỉnh Bàn Cờ"},
{"Name": "Khu du lịch dã ngoại Trung Lương"},
{"Name": "Ngũ Hành Sơn"},
{"Name": "Bãi Rạng"},
{"Name": "Chùa Linh Ứng"},
{"Name": "Động Nàng Tiên"},
{"Name": "Sông Hàn và 4 cây cầu kỉ lục"}
]